general_knowledge_agent/__init__.py
general_knowledge_agent/agent.py
general_knowledge_agent/inference.py
general_knowledge_agent-2.15.0.dist-info/METADATA
general_knowledge_agent-2.15.0.dist-info/WHEEL
general_knowledge_agent-2.15.0.dist-info/top_level.txt
general_knowledge_agent-2.15.0.dist-info/RECORD
